{"cameraMode":{"drawMode":0,"name":"Shaded","section":"Shading Mode"},"sceneLighting":true,"audioPlay":false,"sceneViewState":{"showFog":true,"showMaterialUpdate":false,"showSkybox":true,"showFlares":true,"showImageEffects":true,"showParticleSystems":true,"showVisualEffectGraphs":true,"m_FxEnabled":true},"in2DMode":false,"pivot":{"x":-5.987190246582031,"y":2.867971420288086,"z":4.746588706970215},"rotation":{"x":0.08724597096443176,"y":-0.7911535501480103,"z":0.11618266999721527,"w":0.5941141247749329},"size":6.572131156921387,"orthographic":false}